nanoleafapi/__init__.py
nanoleafapi/digital_twin.py
nanoleafapi/discovery.py
nanoleafapi/nanoleaf.py
nanoleafapi/test_nanoleaf.py
nanoleafapi-2.1.2.dist-info/LICENSE
nanoleafapi-2.1.2.dist-info/METADATA
nanoleafapi-2.1.2.dist-info/WHEEL
nanoleafapi-2.1.2.dist-info/entry_points.txt
nanoleafapi-2.1.2.dist-info/top_level.txt
nanoleafapi-2.1.2.dist-info/RECORD
