Metadata-Version: 2.1
Name: nanoleafapi
Version: 2.1.2
Summary: A Python 3 wrapper for the Nanoleaf OpenAPI, for use when controlling the Light Panels, Canvas and Shapes (including Hexagons)
Home-page: https://github.com/MylesMor/nanoleafapi
Author: MylesMor
Author-email: hello@mylesmor.dev
License: UNKNOWN
Platform: UNKNOWN
Classifier: Programming Language :: Python :: 3
Classifier: License :: OSI Approved :: MIT License
Classifier: Operating System :: OS Independent
Requires-Python: >=3.6
